scrapy_ive/__init__.py
scrapy_ive/item.py
scrapy_ive/core/__init__.py
scrapy_ive/core/downloader.py
scrapy_ive/core/engine.py
scrapy_ive/core/pipeline.py
scrapy_ive/core/scheduler.py
scrapy_ive/core/spider.py
scrapy_ive/http/__init__.py
scrapy_ive/http/request.py
scrapy_ive/http/response.py
scrapy_ive/middlewares/__init__.py
scrapy_ive/middlewares/downloader_middlewares.py
scrapy_ive/middlewares/spider_middlewares.py
scrapy_ive-1.1.dist-info/LICENSE
scrapy_ive-1.1.dist-info/METADATA
scrapy_ive-1.1.dist-info/WHEEL
scrapy_ive-1.1.dist-info/top_level.txt
scrapy_ive-1.1.dist-info/zip-safe
scrapy_ive-1.1.dist-info/RECORD
